pyopen189/__init__.py
pyopen189/sig.py
pyopen189/util.py
pyopen189-0.3.dist-info/DESCRIPTION.rst
pyopen189-0.3.dist-info/METADATA
pyopen189-0.3.dist-info/RECORD
pyopen189-0.3.dist-info/WHEEL
pyopen189-0.3.dist-info/metadata.json
pyopen189-0.3.dist-info/top_level.txt
